<Properties StartupConfiguration="{9A0E540D-E43C-ED8D-2FC9-63FAC861DFF5}|">
  <MonoDevelop.Ide.Workbench ActiveDocument="Assets/Script/LeenTweenAnimations1.cs">
    <Files>
      <File FileName="Assets/Script/BallManager.cs" Line="9" Column="27" />
      <File FileName="Assets/Script/BalanceTheBall.cs" />
      <File FileName="Assets/Script/LeenTweenAnimations1.cs" Line="53" Column="56" />
    </Files>
    <Pads>
      <Pad Id="ProjectPad">
        <State name="__root__">
          <Node name="Physic Based AI" expanded="True">
            <Node name="Assets" expanded="True">
              <Node name="Script" expanded="True">
                <Node name="LeenTweenAnimations1.cs" selected="True" />
              </Node>
            </Node>
          </Node>
        </State>
      </Pad>
    </Pads>
  </MonoDevelop.Ide.Workbench>
  <MonoDevelop.Ide.DebuggingService.PinnedWatches />
  <MonoDevelop.Ide.Workspace ActiveConfiguration="Debug" />
  <MonoDevelop.Ide.ItemProperties.Assembly-CSharp PreferredExecutionTarget="7d0e8671-9f02-4cf9-987d-ef0136e055ae" />
  <MonoDevelop.Ide.DebuggingService.Breakpoints>
    <BreakpointStore />
  </MonoDevelop.Ide.DebuggingService.Breakpoints>
  <MultiItemStartupConfigurations />
</Properties>